[
  {
    "title": "Miwok 100k Photos!",
    "url": "https://tonywithasony.smugmug.com/Miwok-100k-2025",
    "type": "photos"
  },
  {
    "title": "Big Alta Photos!",
    "url": "https://gallery.tonywithasony.com/bigalta25/",
    "type": "photos"
  },
  {
    "title": "norda 005 review",
    "url": "https://youtu.be/kmiIDTXBfz0",
    "type": "video"
  },
  {
    "title": "TRE Recap with David Lam",
    "url": "https://youtu.be/Uc0_eKdD8f8",
    "type": "video"
  },
  {
    "title": "Dipsea Generations Film Fundraiser",
    "url": "https://seedandspark.com/fund/dipsea-generations#story",
    "type": "video"
  },
  {
    "title": "Portfolio Website",
    "url": "/",
    "type": "link"
  },
  {
    "title": "Headlands 27K",
    "url": "https://gallery.tonywithasony.com/headlands27k/",
    "type": "photos"
  },
  {
    "title": "Mingling with David Lam",
    "url": "https://youtu.be/blj9cP_8xZE",
    "type": "video"
  },
  {
    "title": "Dipsea 2024 Photos",
    "url": "https://gallery.tonywithasony.com/dipsea24/",
    "type": "photos"
  },
  {
    "title": "Miwok 100k Photos",
    "url": "https://gallery.tonywithasony.com/miwok100k2024/",
    "type": "photos"
  },
  {
    "title": "The Big Alta Photos",
    "url": "https://gallery.tonywithasony.com/thebigalta/",
    "type": "photos"
  },
  {
    "title": "Trail Shoe Reviews by David and Tony",
    "url": "https://www.youtube.com/playlist?list=PL9T1pYHaS7g4z76DKoa-ckbX0tdvyEHSK",
    "type": "video"
  },
  {
    "title": "Small Steps - Eleanor Scholz",
    "url": "https://youtu.be/2xk4_wgNDBQ",
    "type": "video"
  },
  {
    "title": "You Deserve It - Rebecca Murillo",
    "url": "https://youtu.be/5Wc1b52yEsk",
    "type": "video"
  },
  {
    "title": "Black Canyon 100k Photos!",
    "url": "https://www.dropbox.com/sh/fwalx317yhg953i/AACN9qgO-Y2oK-4sVi1ziAzMa?dl=0",
    "type": "photos"
  },
  {
    "title": "Bandera 100k Recap!",
    "url": "https://www.trailrunnermag.com/people/news-people/bandera-100k-2023/",
    "type": "link"
  },
  {
    "title": "Bandera 100k 2023!",
    "url": "https://www.dropbox.com/sh/x71v51xocp005a9/AABjiv8kFBtoQ7tLFpYWRHFaa?dl=0",
    "type": "photos"
  },
  {
    "title": "Urban Oasis - a love letter to San Francisco",
    "url": "https://vimeo.com/721214409",
    "type": "video"
  },
  {
    "title": "Mammoth Trail Festival Photos!",
    "url": "https://drive.google.com/drive/folders/1VJcGj5ZHwfhtcU5HkkmlAww6ocMPMFvz?usp=sharing",
    "type": "photos"
  },
  {
    "title": "Strong Moms with Erika Hoagland",
    "url": "https://youtu.be/oSgOieM4hRU",
    "type": "video"
  },
  {
    "title": "The Next Generation with José Cruz",
    "url": "https://youtu.be/YJjZkaiHGP4",
    "type": "video"
  }
]
